gnu_jango/__init__.py
gnu_jango/asgi.py
gnu_jango/settings.py
gnu_jango/test.py
gnu_jango/urls.py
gnu_jango/wsgi.py
gnu_jango-0.1.dist-info/METADATA
gnu_jango-0.1.dist-info/WHEEL
gnu_jango-0.1.dist-info/top_level.txt
gnu_jango-0.1.dist-info/RECORD
